cruft/__init__.py
cruft/__main__.py
cruft/_cli.py
cruft/_commands/__init__.py
cruft/_commands/check.py
cruft/_commands/create.py
cruft/_commands/diff.py
cruft/_commands/link.py
cruft/_commands/update.py
cruft/_commands/utils/__init__.py
cruft/_commands/utils/clean.py
cruft/_commands/utils/cookiecutter.py
cruft/_commands/utils/cruft.py
cruft/_commands/utils/diff.py
cruft/_commands/utils/generate.py
cruft/_commands/utils/iohelper.py
cruft/_commands/utils/nested.py
cruft/_commands/utils/validate.py
cruft/_logo.py
cruft/_version.py
cruft/exceptions.py
cruft/py.typed
cruft_iai-0.1.1.dist-info/LICENSE
cruft_iai-0.1.1.dist-info/METADATA
cruft_iai-0.1.1.dist-info/WHEEL
cruft_iai-0.1.1.dist-info/entry_points.txt
cruft_iai-0.1.1.dist-info/RECORD
